hello_world/__init__.py
hello_world/__main__.py
hello_world/data/index.html
hello_world_fbrilej-0.0.3.dist-info/METADATA
hello_world_fbrilej-0.0.3.dist-info/WHEEL
hello_world_fbrilej-0.0.3.dist-info/top_level.txt
hello_world_fbrilej-0.0.3.dist-info/RECORD
