Metadata-Version: 2.1
Name: hello-world-fbrilej
Version: 0.0.3
Summary: A hello world package.
Home-page: https://github.com/smaato
Author: Felix Brilej
Author-email: felix.brilej@smaato.com
License: UNKNOWN
Platform: UNKNOWN
Classifier: Programming Language :: Python :: 3
Classifier: License :: OSI Approved :: MIT License
Classifier: Operating System :: OS Independent
Requires-Python: >=3.6
Requires-Dist: bottle (==0.12.17)
